README.md
setup.py
bin/gkeep_sync
bin/gkeep_update_config
gkeep_sync/__init__.py
gkeep_sync/__main__.py
gkeep_sync/generate_config.py
gkeep_sync/sync_note.py
gkeep_sync/sync_server.py
gkeep_sync/utils.py
gkeep_sync.egg-info/PKG-INFO
gkeep_sync.egg-info/SOURCES.txt
gkeep_sync.egg-info/dependency_links.txt
gkeep_sync.egg-info/requires.txt
gkeep_sync.egg-info/top_level.txt