Metadata-Version: 2.1
Name: gkeep-sync
Version: 0.0.1b0
Summary: A Service that syncs your Google Keep notes with your local file system
Home-page: https://github.com/kanevk/gkeep-files-sync
Author: Kamen Kanev
Author-email: kamen.e.kanev@gmail.com
License: MIT
Download-URL: https://github.com/kanevk/gkeep-files-sync/archive/0.0.1-alpha.tar.gz
Keywords: google keep,keep,notes
Platform: UNKNOWN
Classifier: Development Status :: 3 - Alpha
Classifier: Programming Language :: Python :: 3
Classifier: License :: OSI Approved :: MIT License
Classifier: Operating System :: Unix
Classifier: Operating System :: MacOS
Requires-Python: >=3.6
